{
    "Match":{
        "Title":{
            "div_code":"PFC",
            "div_name":"PRENATIONAL FEMININES",
            "div_pool":"Poule C",
            "match_number":"PFCA012",
            "match_day":"04",
            "city":"CLERMONT FERRAND",
            "gym":"RAYMOND PERRIER",
            "category":"SENIOR | FEMININE",
            "ligue":"Ligue AUVERGNE-RH\u00d4NE-ALPES",
            "date":"2021-10-23 15:00:00",
            "team_1":"STADE CLERMONTOIS",
            "team_2":"AL CEBAZAT VB"
        },
        "Sets":{
            "Teams":{
                "Set 1":{
                    "Name":{
                        "Team 1":"STADE CLERMONTOIS",
                        "Team 2":"AL CEBAZAT VB"
                    },
                    "Starting":{
                        "Team 1":"Reception",
                        "Team 2":"Service"
                    }
                },
                "Set 2":{
                    "Name":{
                        "Team 1":"STADE CLERMONTOIS",
                        "Team 2":"AL CEBAZAT VB"
                    },
                    "Starting":{
                        "Team 1":"Service",
                        "Team 2":"Reception"
                    }
                },
                "Set 3":{
                    "Name":{
                        "Team 1":"STADE CLERMONTOIS",
                        "Team 2":"AL CEBAZAT VB"
                    },
                    "Starting":{
                        "Team 1":"Reception",
                        "Team 2":"Service"
                    }
                },
                "Set 4":0,
                "Set 5":0
            },
            "Time":{
                "Set 1":{
                    "Time":{
                        "Start":"2021-10-23 15:00:00",
                        "End":"2021-10-23 15:27:00"
                    }
                },
                "Set 2":{
                    "Time":{
                        "Start":"2021-10-23 15:30:00",
                        "End":"2021-10-23 16:01:00"
                    }
                },
                "Set 3":{
                    "Time":{
                        "Start":"2021-10-23 16:04:00",
                        "End":"2021-10-23 16:28:00"
                    }
                },
                "Set 4":0,
                "Set 5":0
            },
            "Substitutions 1":{
                "Set 1":{
                    "I":{
                        "0":11.0,
                        "1":null,
                        "2":null
                    },
                    "II":{
                        "0":2.0,
                        "1":null,
                        "2":null
                    },
                    "III":{
                        "0":7.0,
                        "1":null,
                        "2":null
                    },
                    "IV":{
                        "0":4.0,
                        "1":null,
                        "2":null
                    },
                    "V":{
                        "0":"12",
                        "1":"8",
                        "2":"11:17"
                    },
                    "VI":{
                        "0":14.0,
                        "1":null,
                        "2":null
                    }
                },
                "Set 2":{
                    "I":{
                        "0":3.0,
                        "1":null,
                        "2":null
                    },
                    "II":{
                        "0":"7",
                        "1":"8",
                        "2":"5:14"
                    },
                    "III":{
                        "0":6.0,
                        "1":null,
                        "2":null
                    },
                    "IV":{
                        "0":12.0,
                        "1":null,
                        "2":null
                    },
                    "V":{
                        "0":14.0,
                        "1":null,
                        "2":null
                    },
                    "VI":{
                        "0":11.0,
                        "1":null,
                        "2":null
                    }
                },
                "Set 3":{
                    "I":{
                        "0":"11",
                        "1":"6",
                        "2":"5:13"
                    },
                    "II":{
                        "0":3.0,
                        "1":null,
                        "2":null
                    },
                    "III":{
                        "0":7.0,
                        "1":null,
                        "2":null
                    },
                    "IV":{
                        "0":4.0,
                        "1":null,
                        "2":null
                    },
                    "V":{
                        "0":"12",
                        "1":"8",
                        "2":"5:10"
                    },
                    "VI":{
                        "0":14.0,
                        "1":null,
                        "2":null
                    }
                },
                "Set 4":0,
                "Set 5":0
            },
            "Substitutions 2":{
                "Set 1":{
                    "I":{
                        "0":2.0,
                        "1":null,
                        "2":null
                    },
                    "II":{
                        "0":3.0,
                        "1":null,
                        "2":null
                    },
                    "III":{
                        "0":4.0,
                        "1":null,
                        "2":null
                    },
                    "IV":{
                        "0":6.0,
                        "1":null,
                        "2":null
                    },
                    "V":{
                        "0":"13",
                        "1":"9",
                        "2":"21:15"
                    },
                    "VI":{
                        "0":"12",
                        "1":"5",
                        "2":"14:9"
                    }
                },
                "Set 2":{
                    "I":{
                        "0":"12",
                        "1":"10",
                        "2":"20:13"
                    },
                    "II":{
                        "0":2.0,
                        "1":null,
                        "2":null
                    },
                    "III":{
                        "0":3.0,
                        "1":null,
                        "2":null
                    },
                    "IV":{
                        "0":"5",
                        "1":"4",
                        "2":"19:12"
                    },
                    "V":{
                        "0":6.0,
                        "1":null,
                        "2":null
                    },
                    "VI":{
                        "0":"13",
                        "1":"8",
                        "2":"20:13"
                    }
                },
                "Set 3":{
                    "I":{
                        "0":"9",
                        "1":"8",
                        "2":"20:7"
                    },
                    "II":{
                        "0":"5",
                        "1":"10",
                        "2":"20:7"
                    },
                    "III":{
                        "0":2.0,
                        "1":null,
                        "2":null
                    },
                    "IV":{
                        "0":"3",
                        "1":"13",
                        "2":"19:6"
                    },
                    "V":{
                        "0":"12",
                        "1":"4",
                        "2":"19:7"
                    },
                    "VI":{
                        "0":6.0,
                        "1":null,
                        "2":null
                    }
                },
                "Set 4":0,
                "Set 5":0
            },
            "Serves 1":{
                "Set 1":{
                    "I":{
                        "0":null,
                        "1":11.0
                    },
                    "II":{
                        "0":"4",
                        "1":13
                    },
                    "III":{
                        "0":"5",
                        "1":14
                    },
                    "IV":{
                        "0":"6",
                        "1":15
                    },
                    "V":{
                        "0":"7",
                        "1":16
                    },
                    "VI":{
                        "0":"9",
                        "1":null
                    }
                },
                "Set 2":{
                    "I":{
                        "0":"0",
                        "1":8,
                        "2":21
                    },
                    "II":{
                        "0":"1",
                        "1":9.0,
                        "2":null
                    },
                    "III":{
                        "0":"2",
                        "1":12.0,
                        "2":null
                    },
                    "IV":{
                        "0":"3",
                        "1":17.0,
                        "2":null
                    },
                    "V":{
                        "0":"5",
                        "1":18.0,
                        "2":null
                    },
                    "VI":{
                        "0":"6",
                        "1":19.0,
                        "2":null
                    }
                },
                "Set 3":{
                    "I":{
                        "0":null,
                        "1":8.0
                    },
                    "II":{
                        "0":"2",
                        "1":10
                    },
                    "III":{
                        "0":"4",
                        "1":12
                    },
                    "IV":{
                        "0":"5",
                        "1":null
                    },
                    "V":{
                        "0":"6",
                        "1":null
                    },
                    "VI":{
                        "0":"7",
                        "1":null
                    }
                },
                "Set 4":0,
                "Set 5":0
            },
            "Serves 2":{
                "Set 1":{
                    "I":{
                        "0":"3",
                        "1":18
                    },
                    "II":{
                        "0":"4",
                        "1":19
                    },
                    "III":{
                        "0":"6",
                        "1":20
                    },
                    "IV":{
                        "0":"12",
                        "1":23
                    },
                    "V":{
                        "0":"13",
                        "1":25
                    },
                    "VI":{
                        "0":"14",
                        "1":null
                    }
                },
                "Set 2":{
                    "I":{
                        "0":null,
                        "1":16.0,
                        "2":23.0
                    },
                    "II":{
                        "0":"3",
                        "1":17,
                        "2":25
                    },
                    "III":{
                        "0":"5",
                        "1":18.0,
                        "2":null
                    },
                    "IV":{
                        "0":"6",
                        "1":20.0,
                        "2":null
                    },
                    "V":{
                        "0":"11",
                        "1":21.0,
                        "2":null
                    },
                    "VI":{
                        "0":"14",
                        "1":22.0,
                        "2":null
                    }
                },
                "Set 3":{
                    "I":{
                        "0":"0",
                        "1":21
                    },
                    "II":{
                        "0":"3",
                        "1":22
                    },
                    "III":{
                        "0":"5",
                        "1":25
                    },
                    "IV":{
                        "0":"14",
                        "1":null
                    },
                    "V":{
                        "0":"19",
                        "1":null
                    },
                    "VI":{
                        "0":"20",
                        "1":null
                    }
                },
                "Set 4":0,
                "Set 5":0
            },
            "Timeouts 1":{
                "Set 1":{
                    "T":{
                        "0":"14:20",
                        "1":"15:22"
                    }
                },
                "Set 2":{
                    "T":{
                        "0":"3:11",
                        "1":"9:18"
                    }
                },
                "Set 3":{
                    "T":{
                        "0":"6:18"
                    }
                },
                "Set 4":0,
                "Set 5":0
            },
            "Timeouts 2":{
                "Set 1":{
                    "T":{

                    }
                },
                "Set 2":{
                    "T":{

                    }
                },
                "Set 3":{
                    "T":{

                    }
                },
                "Set 4":0,
                "Set 5":0
            }
        },
        "Teams":{
            "Name":{
                "Team 1":"STADE CLERMONTOIS",
                "Team 2":"AL CEBAZAT VB"
            },
            "Players":{
                "Team 1":{
                    "N\u00b0":{
                        "0":2,
                        "1":3,
                        "2":4,
                        "3":6,
                        "4":7,
                        "5":8,
                        "6":10,
                        "7":11,
                        "8":12,
                        "9":14
                    },
                    "Nom Pr\u00e9nom":{
                        "0":"JOIN CECILE",
                        "1":"LARUE CHARLOTTE",
                        "2":"VIVANCOS MARIE",
                        "3":"CHEVAUX CLEMENCE",
                        "4":"SIMONITTI CHRISTELLE",
                        "5":"TAILLE AMELIE",
                        "6":"SEGUIN CHLOE",
                        "7":"NOUAR RIM",
                        "8":"NAQUIN CLARA",
                        "9":"RAPHANAUD MATTY"
                    },
                    "Licence":{
                        "0":1688863,
                        "1":1524960,
                        "2":2158020,
                        "3":1739820,
                        "4":1410201,
                        "5":2205397,
                        "6":2089637,
                        "7":2098782,
                        "8":1996717,
                        "9":1767892
                    }
                },
                "Team 2":{
                    "N\u00b0":{
                        "0":2,
                        "1":3,
                        "2":4,
                        "3":5,
                        "4":6,
                        "5":8,
                        "6":9,
                        "7":10,
                        "8":12,
                        "9":13
                    },
                    "Nom Pr\u00e9nom":{
                        "0":"GREGOIRE VALEX LAURE",
                        "1":"VIDAL TIPHAINE",
                        "2":"GOMEZ JULIE",
                        "3":"PIRES ANDREA",
                        "4":"RIQUE MORGANE",
                        "5":"GRAND JOHANNA",
                        "6":"MONESTIER CAROLINE",
                        "7":"CHABRIAS ELEANORE",
                        "8":"MARTIN CELINE",
                        "9":"CHABOSY LAURA"
                    },
                    "Licence":{
                        "0":2088857,
                        "1":1567770,
                        "2":1765742,
                        "3":1571636,
                        "4":1735913,
                        "5":2262013,
                        "6":1192413,
                        "7":2308849,
                        "8":2413432,
                        "9":2051173
                    }
                }
            },
            "Liberos":{
                "Team 1":{
                    "N\u00b0":{
                        "0":10
                    },
                    "Nom Pr\u00e9nom":{
                        "0":"SEGUIN CHLOE"
                    },
                    "Licence":{
                        "0":2089637
                    }
                },
                "Team 2":{
                    "N\u00b0":{

                    },
                    "Nom Pr\u00e9nom":{

                    },
                    "Licence":{

                    }
                }
            },
            "Officials":{
                "Team 1":{
                    "N\u00b0":{
                        "0":"EA"
                    },
                    "Nom Pr\u00e9nom":{
                        "0":"HOUILLON IRYNA"
                    },
                    "Licence":{
                        "0":2193048
                    }
                },
                "Team 2":{
                    "N\u00b0":{
                        "0":"EA"
                    },
                    "Nom Pr\u00e9nom":{
                        "0":"SEGURA JULIEN"
                    },
                    "Licence":{
                        "0":1602742
                    }
                }
            }
        },
        "Results":{
            "winner":"AL CEBAZAT VB",
            "score":"3\/0"
        },
        "Referees":{
            "NOM Pr\u00e9nom":{
                "1er":"LUSERGA ELOISE",
                "2\u00e8me":"MARTIN GUILLAUME",
                "Marqueur":"ROLHION GILLES",
                "Marq.Ass":".",
                "nan":null
            },
            "Ligue":{
                "1er":"AURA",
                "2\u00e8me":"AURA",
                "Marqueur":"AURA",
                "Marq.Ass":null,
                "nan":"Juges"
            },
            "Licence":{
                "1er":1846926.0,
                "2\u00e8me":1343332.0,
                "Marqueur":1891848.0,
                "Marq.Ass":null,
                "nan":null
            }
        },
        "Penalties":{

        }
    }
}