{
    "Match":{
        "Title":{
            "div_code":"3FC",
            "div_name":"NATIONALE 3 FEMININE",
            "div_pool":"Poule C",
            "match_number":"3FC033",
            "match_day":"06",
            "city":"SEYSSINS",
            "gym":"YVES BROUZET",
            "category":"SENIOR | FEMININE",
            "ligue":"Comp\u00e9titions Nationales SENIORS",
            "date":"2019-11-24 15:00:00",
            "team_1":"UNION AS. SEYSSINOISE V.B.",
            "team_2":"UNION SPORTIVE ISSOIRIENNE VOLLEY-BALL"
        },
        "Sets":{
            "Teams":{
                "Set 1":{
                    "Name":{
                        "Team 1":"UNION AS. SEYSSINOISE",
                        "Team 2":"UNION SPORTIVE ISSOIRI"
                    },
                    "Starting":{
                        "Team 1":"Service",
                        "Team 2":"Reception"
                    }
                },
                "Set 2":{
                    "Name":{
                        "Team 1":"UNION AS. SEYSSINOISE",
                        "Team 2":"UNION SPORTIVE ISSOIRI"
                    },
                    "Starting":{
                        "Team 1":"Reception",
                        "Team 2":"Service"
                    }
                },
                "Set 3":{
                    "Name":{
                        "Team 1":"UNION AS. SEYSSINOISE",
                        "Team 2":"UNION SPORTIVE ISSOIRI"
                    },
                    "Starting":{
                        "Team 1":"Service",
                        "Team 2":"Reception"
                    }
                },
                "Set 4":{
                    "Name":{
                        "Team 1":"UNION AS. SEYSSINOISE",
                        "Team 2":"UNION SPORTIVE ISSOIRI"
                    },
                    "Starting":{
                        "Team 1":"Reception",
                        "Team 2":"Service"
                    }
                },
                "Set 5":0
            },
            "Time":{
                "Set 1":{
                    "Time":{
                        "Start":"2019-11-24 15:00:00",
                        "End":"2019-11-24 15:27:00"
                    }
                },
                "Set 2":{
                    "Time":{
                        "Start":"2019-11-24 15:31:00",
                        "End":"2019-11-24 15:51:00"
                    }
                },
                "Set 3":{
                    "Time":{
                        "Start":"2019-11-24 15:55:00",
                        "End":"2019-11-24 16:18:00"
                    }
                },
                "Set 4":{
                    "Time":{
                        "Start":"2019-11-24 16:21:00",
                        "End":"2019-11-24 16:44:00"
                    }
                },
                "Set 5":0
            },
            "Substitutions 1":{
                "Set 1":{
                    "I":{
                        "0":"6",
                        "1":"1",
                        "2":"22:23",
                        "3":"25:25"
                    },
                    "II":{
                        "0":4.0,
                        "1":null,
                        "2":null,
                        "3":null
                    },
                    "III":{
                        "0":8.0,
                        "1":null,
                        "2":null,
                        "3":null
                    },
                    "IV":{
                        "0":"9",
                        "1":"10",
                        "2":"16:18",
                        "3":null
                    },
                    "V":{
                        "0":2.0,
                        "1":null,
                        "2":null,
                        "3":null
                    },
                    "VI":{
                        "0":11.0,
                        "1":null,
                        "2":null,
                        "3":null
                    }
                },
                "Set 2":{
                    "I":{
                        "0":"6",
                        "1":"1",
                        "2":"18:12"
                    },
                    "II":{
                        "0":4.0,
                        "1":null,
                        "2":null
                    },
                    "III":{
                        "0":8.0,
                        "1":null,
                        "2":null
                    },
                    "IV":{
                        "0":10.0,
                        "1":null,
                        "2":null
                    },
                    "V":{
                        "0":2.0,
                        "1":null,
                        "2":null
                    },
                    "VI":{
                        "0":11.0,
                        "1":null,
                        "2":null
                    }
                },
                "Set 3":{
                    "I":{
                        "0":"6",
                        "1":"1",
                        "2":"7:8",
                        "3":"11:18"
                    },
                    "II":{
                        "0":4.0,
                        "1":null,
                        "2":null,
                        "3":null
                    },
                    "III":{
                        "0":8.0,
                        "1":null,
                        "2":null,
                        "3":null
                    },
                    "IV":{
                        "0":"18",
                        "1":"9",
                        "2":"17:20",
                        "3":null
                    },
                    "V":{
                        "0":"2",
                        "1":"10",
                        "2":"7:9",
                        "3":null
                    },
                    "VI":{
                        "0":11.0,
                        "1":null,
                        "2":null,
                        "3":null
                    }
                },
                "Set 4":{
                    "I":{
                        "0":"6",
                        "1":"1",
                        "2":"18:14"
                    },
                    "II":{
                        "0":4.0,
                        "1":null,
                        "2":null
                    },
                    "III":{
                        "0":8.0,
                        "1":null,
                        "2":null
                    },
                    "IV":{
                        "0":10.0,
                        "1":null,
                        "2":null
                    },
                    "V":{
                        "0":2.0,
                        "1":null,
                        "2":null
                    },
                    "VI":{
                        "0":11.0,
                        "1":null,
                        "2":null
                    }
                },
                "Set 5":0
            },
            "Substitutions 2":{
                "Set 1":{
                    "I":{
                        "0":17.0,
                        "1":null,
                        "2":null,
                        "3":null
                    },
                    "II":{
                        "0":6.0,
                        "1":null,
                        "2":null,
                        "3":null
                    },
                    "III":{
                        "0":10.0,
                        "1":null,
                        "2":null,
                        "3":null
                    },
                    "IV":{
                        "0":7.0,
                        "1":null,
                        "2":null,
                        "3":null
                    },
                    "V":{
                        "0":"4",
                        "1":"18",
                        "2":"22:20",
                        "3":"25:25"
                    },
                    "VI":{
                        "0":11.0,
                        "1":null,
                        "2":null,
                        "3":null
                    }
                },
                "Set 2":{
                    "I":{
                        "0":17.0,
                        "1":null,
                        "2":null
                    },
                    "II":{
                        "0":6.0,
                        "1":null,
                        "2":null
                    },
                    "III":{
                        "0":10.0,
                        "1":null,
                        "2":null
                    },
                    "IV":{
                        "0":7.0,
                        "1":null,
                        "2":null
                    },
                    "V":{
                        "0":"4",
                        "1":"14",
                        "2":"13:19"
                    },
                    "VI":{
                        "0":11.0,
                        "1":null,
                        "2":null
                    }
                },
                "Set 3":{
                    "I":{
                        "0":17
                    },
                    "II":{
                        "0":6
                    },
                    "III":{
                        "0":10
                    },
                    "IV":{
                        "0":7
                    },
                    "V":{
                        "0":14
                    },
                    "VI":{
                        "0":11
                    }
                },
                "Set 4":{
                    "I":{
                        "0":17
                    },
                    "II":{
                        "0":6
                    },
                    "III":{
                        "0":10
                    },
                    "IV":{
                        "0":7
                    },
                    "V":{
                        "0":14
                    },
                    "VI":{
                        "0":11
                    }
                },
                "Set 5":0
            },
            "Serves 1":{
                "Set 1":{
                    "I":{
                        "0":"0",
                        "1":7,
                        "2":16,
                        "3":25
                    },
                    "II":{
                        "0":"1",
                        "1":8,
                        "2":18,
                        "3":27
                    },
                    "III":{
                        "0":"2",
                        "1":11.0,
                        "2":19.0,
                        "3":null
                    },
                    "IV":{
                        "0":"3",
                        "1":12.0,
                        "2":20.0,
                        "3":null
                    },
                    "V":{
                        "0":"4",
                        "1":13.0,
                        "2":21.0,
                        "3":null
                    },
                    "VI":{
                        "0":"6",
                        "1":14.0,
                        "2":24.0,
                        "3":null
                    }
                },
                "Set 2":{
                    "I":{
                        "0":null,
                        "1":13.0,
                        "2":24.0
                    },
                    "II":{
                        "0":"3",
                        "1":14,
                        "2":25
                    },
                    "III":{
                        "0":"4",
                        "1":15.0,
                        "2":null
                    },
                    "IV":{
                        "0":"6",
                        "1":17.0,
                        "2":null
                    },
                    "V":{
                        "0":"7",
                        "1":19.0,
                        "2":null
                    },
                    "VI":{
                        "0":"11",
                        "1":21.0,
                        "2":null
                    }
                },
                "Set 3":{
                    "I":{
                        "0":"1",
                        "1":9
                    },
                    "II":{
                        "0":"4",
                        "1":11
                    },
                    "III":{
                        "0":"5",
                        "1":16
                    },
                    "IV":{
                        "0":"6",
                        "1":17
                    },
                    "V":{
                        "0":"7",
                        "1":19
                    },
                    "VI":{
                        "0":"8",
                        "1":null
                    }
                },
                "Set 4":{
                    "I":{
                        "0":null,
                        "1":10.0,
                        "2":23.0
                    },
                    "II":{
                        "0":"1",
                        "1":11,
                        "2":25
                    },
                    "III":{
                        "0":"3",
                        "1":14.0,
                        "2":null
                    },
                    "IV":{
                        "0":"5",
                        "1":16.0,
                        "2":null
                    },
                    "V":{
                        "0":"6",
                        "1":19.0,
                        "2":null
                    },
                    "VI":{
                        "0":"8",
                        "1":21.0,
                        "2":null
                    }
                },
                "Set 5":0
            },
            "Serves 2":{
                "Set 1":{
                    "I":{
                        "0":null,
                        "1":8.0,
                        "2":18.0,
                        "3":24.0
                    },
                    "II":{
                        "0":"2",
                        "1":9,
                        "2":19,
                        "3":25
                    },
                    "III":{
                        "0":"3",
                        "1":10.0,
                        "2":20.0,
                        "3":null
                    },
                    "IV":{
                        "0":"5",
                        "1":13.0,
                        "2":21.0,
                        "3":null
                    },
                    "V":{
                        "0":"6",
                        "1":14.0,
                        "2":22.0,
                        "3":null
                    },
                    "VI":{
                        "0":"7",
                        "1":17.0,
                        "2":23.0,
                        "3":null
                    }
                },
                "Set 2":{
                    "I":{
                        "0":"0",
                        "1":7,
                        "2":16
                    },
                    "II":{
                        "0":"2",
                        "1":9.0,
                        "2":null
                    },
                    "III":{
                        "0":"3",
                        "1":10.0,
                        "2":null
                    },
                    "IV":{
                        "0":"4",
                        "1":12.0,
                        "2":null
                    },
                    "V":{
                        "0":"5",
                        "1":13.0,
                        "2":null
                    },
                    "VI":{
                        "0":"6",
                        "1":14.0,
                        "2":null
                    }
                },
                "Set 3":{
                    "I":{
                        "0":null,
                        "1":13.0
                    },
                    "II":{
                        "0":"2",
                        "1":14
                    },
                    "III":{
                        "0":"4",
                        "1":18
                    },
                    "IV":{
                        "0":"6",
                        "1":19
                    },
                    "V":{
                        "0":"8",
                        "1":22
                    },
                    "VI":{
                        "0":"12",
                        "1":25
                    }
                },
                "Set 4":{
                    "I":{
                        "0":"0",
                        "1":11,
                        "2":17
                    },
                    "II":{
                        "0":"1",
                        "1":12.0,
                        "2":null
                    },
                    "III":{
                        "0":"2",
                        "1":13.0,
                        "2":null
                    },
                    "IV":{
                        "0":"3",
                        "1":14.0,
                        "2":null
                    },
                    "V":{
                        "0":"7",
                        "1":15.0,
                        "2":null
                    },
                    "VI":{
                        "0":"10",
                        "1":16.0,
                        "2":null
                    }
                },
                "Set 5":0
            },
            "Timeouts 1":{
                "Set 1":{
                    "T":{

                    }
                },
                "Set 2":{
                    "T":{

                    }
                },
                "Set 3":{
                    "T":{

                    }
                },
                "Set 4":{
                    "T":{

                    }
                },
                "Set 5":0
            },
            "Timeouts 2":{
                "Set 1":{
                    "T":{
                        "0":"23:23"
                    }
                },
                "Set 2":{
                    "T":{
                        "0":"5:10"
                    }
                },
                "Set 3":{
                    "T":{

                    }
                },
                "Set 4":{
                    "T":{
                        "0":"14:18",
                        "1":"16:23"
                    }
                },
                "Set 5":0
            }
        },
        "Teams":{
            "Name":{
                "Team 1":"UNION AS. SEYSSINOISE V.B.",
                "Team 2":"UNION SPORTIVE ISSOIRIENNE VOL"
            },
            "Players":{
                "Team 1":{
                    "N\u00b0":{
                        "0":1,
                        "1":2,
                        "2":4,
                        "3":6,
                        "4":8,
                        "5":9,
                        "6":10,
                        "7":11,
                        "8":14,
                        "9":15,
                        "10":18
                    },
                    "Nom Pr\u00e9nom":{
                        "0":"DEL MEDICO EMILIE",
                        "1":"HOLAIND MARGOT",
                        "2":"MOREL CAMILLE",
                        "3":"GARNIER AMANDINE",
                        "4":"FAURE MONIQUE",
                        "5":"MASELLA DI BILIO JULIA",
                        "6":"TOURTE SABINE",
                        "7":"MONGELLAZ CLARA",
                        "8":"MAURICE NINA",
                        "9":"CHEVRIER SARAH",
                        "10":"FAUNE AUDREY"
                    },
                    "Licence":{
                        "0":1831346,
                        "1":1446705,
                        "2":1993347,
                        "3":1603102,
                        "4":1760774,
                        "5":1914971,
                        "6":2137577,
                        "7":1897695,
                        "8":1898078,
                        "9":1782599,
                        "10":1683346
                    }
                },
                "Team 2":{
                    "N\u00b0":{
                        "0":2,
                        "1":4,
                        "2":6,
                        "3":7,
                        "4":10,
                        "5":11,
                        "6":14,
                        "7":17,
                        "8":18
                    },
                    "Nom Pr\u00e9nom":{
                        "0":"DARQUE JUSTINE",
                        "1":"CALIXTE GRANDISSON LORNA",
                        "2":"WENEHOUA HMADREN",
                        "3":"GIRAUD VIOLAINE",
                        "4":"THIBAUT MERCIER NOEMIE",
                        "5":"TANGOPI FETUAO",
                        "6":"FIAFIALOTO NATHALIE",
                        "7":"DAMAS MARGAUX",
                        "8":"REBERGUE ALINE"
                    },
                    "Licence":{
                        "0":1996286,
                        "1":1875183,
                        "2":2300325,
                        "3":1767570,
                        "4":1529805,
                        "5":2302671,
                        "6":2125682,
                        "7":2053498,
                        "8":1479487
                    }
                }
            },
            "Liberos":{
                "Team 1":{
                    "N\u00b0":{
                        "0":14,
                        "1":15
                    },
                    "Nom Pr\u00e9nom":{
                        "0":"MAURICE NINA",
                        "1":"CHEVRIER SARAH"
                    },
                    "Licence":{
                        "0":1898078,
                        "1":1782599
                    }
                },
                "Team 2":{
                    "N\u00b0":{
                        "0":2
                    },
                    "Nom Pr\u00e9nom":{
                        "0":"DARQUE JUSTINE"
                    },
                    "Licence":{
                        "0":1996286
                    }
                }
            },
            "Officials":{
                "Team 1":{
                    "N\u00b0":{
                        "0":"EA",
                        "1":"EB"
                    },
                    "Nom Pr\u00e9nom":{
                        "0":"MVONGO ESSAMA ORLANDO",
                        "1":"LAPIERRE AURELIEN"
                    },
                    "Licence":{
                        "0":1859628,
                        "1":1446821
                    }
                },
                "Team 2":{
                    "N\u00b0":{

                    },
                    "Nom Pr\u00e9nom":{

                    },
                    "Licence":{

                    }
                }
            }
        },
        "Results":{
            "winner":"UNION AS. SEYSSINOISE",
            "score":"3\/1"
        },
        "Referees":{
            "NOM Pr\u00e9nom":{
                "1er":"PEROTTI MARC",
                "2\u00e8me":"RUAS CEDRIC",
                "Marqueur":"GIOL LOU-ANNE",
                "Marq.Ass":".",
                "R.Salle":"LE MEUR JACQUES"
            },
            "Ligue":{
                "1er":"LIG_ARA",
                "2\u00e8me":"LIG_ARA",
                "Marqueur":"LIG_ARA",
                "Marq.Ass":null,
                "R.Salle":"LIG_ARA"
            },
            "Licence":{
                "1er":540732.0,
                "2\u00e8me":1054883.0,
                "Marqueur":1901852.0,
                "Marq.Ass":null,
                "R.Salle":998641.0
            }
        },
        "Penalties":{

        }
    }
}