{
    "Match":{
        "Title":{
            "div_code":"EFA",
            "div_name":"ELITE FEMININE",
            "div_pool":"POULE A",
            "match_number":"EFA082",
            "match_day":"17",
            "city":"QUIMPER",
            "gym":"HALLE DES SPORTS ERGUE ARMEL",
            "category":"SENIOR | FEMININE",
            "ligue":"Comp\u00e9titions Nationales SENIORS",
            "date":"2021-03-05 20:30:00",
            "team_1":"QUIMPER VOLLEY 29",
            "team_2":"RENNES ETUDIANTS CLUB"
        },
        "Sets":{
            "Teams":{
                "Set 1":{
                    "Name":{
                        "Team 1":"QUIMPER VOLLEY 29",
                        "Team 2":"RENNES ETUDIANTS CLUB"
                    },
                    "Starting":{
                        "Team 1":"Service",
                        "Team 2":"Reception"
                    }
                },
                "Set 2":{
                    "Name":{
                        "Team 1":"QUIMPER VOLLEY 29",
                        "Team 2":"RENNES ETUDIANTS CLUB"
                    },
                    "Starting":{
                        "Team 1":"Reception",
                        "Team 2":"Service"
                    }
                },
                "Set 3":{
                    "Name":{
                        "Team 1":"QUIMPER VOLLEY 29",
                        "Team 2":"RENNES ETUDIANTS CLUB"
                    },
                    "Starting":{
                        "Team 1":"Service",
                        "Team 2":"Reception"
                    }
                },
                "Set 4":{
                    "Name":{
                        "Team 1":"QUIMPER VOLLEY 29",
                        "Team 2":"RENNES ETUDIANTS CLUB"
                    },
                    "Starting":{
                        "Team 1":"Reception",
                        "Team 2":"Service"
                    }
                },
                "Set 5":0
            },
            "Time":{
                "Set 1":{
                    "Time":{
                        "Start":"2021-03-05 20:29:00",
                        "End":"2021-03-05 20:54:00"
                    }
                },
                "Set 2":{
                    "Time":{
                        "Start":"2021-03-05 20:57:00",
                        "End":"2021-03-05 21:21:00"
                    }
                },
                "Set 3":{
                    "Time":{
                        "Start":"2021-03-05 21:24:00",
                        "End":"2021-03-05 21:47:00"
                    }
                },
                "Set 4":{
                    "Time":{
                        "Start":"2021-03-05 21:50:00",
                        "End":"2021-03-05 22:13:00"
                    }
                },
                "Set 5":0
            },
            "Substitutions 1":{
                "Set 1":{
                    "I":{
                        "0":"1",
                        "1":"15",
                        "2":"5:13"
                    },
                    "II":{
                        "0":"10",
                        "1":"12",
                        "2":"5:15"
                    },
                    "III":{
                        "0":9.0,
                        "1":null,
                        "2":null
                    },
                    "IV":{
                        "0":5.0,
                        "1":null,
                        "2":null
                    },
                    "V":{
                        "0":14.0,
                        "1":null,
                        "2":null
                    },
                    "VI":{
                        "0":16.0,
                        "1":null,
                        "2":null
                    }
                },
                "Set 2":{
                    "I":{
                        "0":9
                    },
                    "II":{
                        "0":5
                    },
                    "III":{
                        "0":14
                    },
                    "IV":{
                        "0":16
                    },
                    "V":{
                        "0":15
                    },
                    "VI":{
                        "0":12
                    }
                },
                "Set 3":{
                    "I":{
                        "0":9
                    },
                    "II":{
                        "0":5
                    },
                    "III":{
                        "0":14
                    },
                    "IV":{
                        "0":16
                    },
                    "V":{
                        "0":15
                    },
                    "VI":{
                        "0":12
                    }
                },
                "Set 4":{
                    "I":{
                        "0":9.0,
                        "1":null,
                        "2":null
                    },
                    "II":{
                        "0":5.0,
                        "1":null,
                        "2":null
                    },
                    "III":{
                        "0":14.0,
                        "1":null,
                        "2":null
                    },
                    "IV":{
                        "0":16.0,
                        "1":null,
                        "2":null
                    },
                    "V":{
                        "0":15.0,
                        "1":null,
                        "2":null
                    },
                    "VI":{
                        "0":"12",
                        "1":"1",
                        "2":"24:17"
                    }
                },
                "Set 5":0
            },
            "Substitutions 2":{
                "Set 1":{
                    "I":{
                        "0":"5",
                        "1":"7",
                        "2":"17:6"
                    },
                    "II":{
                        "0":"8",
                        "1":"12",
                        "2":"19:8"
                    },
                    "III":{
                        "0":4.0,
                        "1":null,
                        "2":null
                    },
                    "IV":{
                        "0":14.0,
                        "1":null,
                        "2":null
                    },
                    "V":{
                        "0":13.0,
                        "1":null,
                        "2":null
                    },
                    "VI":{
                        "0":11.0,
                        "1":null,
                        "2":null
                    }
                },
                "Set 2":{
                    "I":{
                        "0":7.0,
                        "1":null,
                        "2":null
                    },
                    "II":{
                        "0":12.0,
                        "1":null,
                        "2":null
                    },
                    "III":{
                        "0":4.0,
                        "1":null,
                        "2":null
                    },
                    "IV":{
                        "0":"14",
                        "1":"8",
                        "2":"12:16"
                    },
                    "V":{
                        "0":13.0,
                        "1":null,
                        "2":null
                    },
                    "VI":{
                        "0":11.0,
                        "1":null,
                        "2":null
                    }
                },
                "Set 3":{
                    "I":{
                        "0":12.0,
                        "1":null,
                        "2":null
                    },
                    "II":{
                        "0":"4",
                        "1":"14",
                        "2":"6:4"
                    },
                    "III":{
                        "0":8.0,
                        "1":null,
                        "2":null
                    },
                    "IV":{
                        "0":13.0,
                        "1":null,
                        "2":null
                    },
                    "V":{
                        "0":11.0,
                        "1":null,
                        "2":null
                    },
                    "VI":{
                        "0":"7",
                        "1":"5",
                        "2":"11:17"
                    }
                },
                "Set 4":{
                    "I":{
                        "0":5
                    },
                    "II":{
                        "0":12
                    },
                    "III":{
                        "0":14
                    },
                    "IV":{
                        "0":8
                    },
                    "V":{
                        "0":13
                    },
                    "VI":{
                        "0":11
                    }
                },
                "Set 5":0
            },
            "Serves 1":{
                "Set 1":{
                    "I":{
                        "0":"1",
                        "1":8
                    },
                    "II":{
                        "0":"2",
                        "1":9
                    },
                    "III":{
                        "0":"3",
                        "1":11
                    },
                    "IV":{
                        "0":"4",
                        "1":14
                    },
                    "V":{
                        "0":"5",
                        "1":16
                    },
                    "VI":{
                        "0":"6",
                        "1":17
                    }
                },
                "Set 2":{
                    "I":{
                        "0":null,
                        "1":13.0,
                        "2":21.0
                    },
                    "II":{
                        "0":"1",
                        "1":15,
                        "2":25
                    },
                    "III":{
                        "0":"3",
                        "1":16.0,
                        "2":null
                    },
                    "IV":{
                        "0":"4",
                        "1":17.0,
                        "2":null
                    },
                    "V":{
                        "0":"6",
                        "1":19.0,
                        "2":null
                    },
                    "VI":{
                        "0":"11",
                        "1":20.0,
                        "2":null
                    }
                },
                "Set 3":{
                    "I":{
                        "0":"0",
                        "1":10
                    },
                    "II":{
                        "0":"1",
                        "1":14
                    },
                    "III":{
                        "0":"2",
                        "1":21
                    },
                    "IV":{
                        "0":"4",
                        "1":24
                    },
                    "V":{
                        "0":"5",
                        "1":25
                    },
                    "VI":{
                        "0":"8",
                        "1":null
                    }
                },
                "Set 4":{
                    "I":{
                        "0":null,
                        "1":14.0,
                        "2":25.0
                    },
                    "II":{
                        "0":"6",
                        "1":17.0,
                        "2":null
                    },
                    "III":{
                        "0":"7",
                        "1":19.0,
                        "2":null
                    },
                    "IV":{
                        "0":"8",
                        "1":21.0,
                        "2":null
                    },
                    "V":{
                        "0":"9",
                        "1":23.0,
                        "2":null
                    },
                    "VI":{
                        "0":"10",
                        "1":24.0,
                        "2":null
                    }
                },
                "Set 5":0
            },
            "Serves 2":{
                "Set 1":{
                    "I":{
                        "0":null,
                        "1":18.0,
                        "2":25.0
                    },
                    "II":{
                        "0":"4",
                        "1":19.0,
                        "2":null
                    },
                    "III":{
                        "0":"5",
                        "1":20.0,
                        "2":null
                    },
                    "IV":{
                        "0":"6",
                        "1":21.0,
                        "2":null
                    },
                    "V":{
                        "0":"9",
                        "1":22.0,
                        "2":null
                    },
                    "VI":{
                        "0":"16",
                        "1":24.0,
                        "2":null
                    }
                },
                "Set 2":{
                    "I":{
                        "0":"3",
                        "1":10,
                        "2":18
                    },
                    "II":{
                        "0":"4",
                        "1":11.0,
                        "2":null
                    },
                    "III":{
                        "0":"5",
                        "1":12.0,
                        "2":null
                    },
                    "IV":{
                        "0":"6",
                        "1":13.0,
                        "2":null
                    },
                    "V":{
                        "0":"7",
                        "1":14.0,
                        "2":null
                    },
                    "VI":{
                        "0":"9",
                        "1":17.0,
                        "2":null
                    }
                },
                "Set 3":{
                    "I":{
                        "0":null,
                        "1":9.0
                    },
                    "II":{
                        "0":"1",
                        "1":10
                    },
                    "III":{
                        "0":"3",
                        "1":11
                    },
                    "IV":{
                        "0":"5",
                        "1":12
                    },
                    "V":{
                        "0":"7",
                        "1":13
                    },
                    "VI":{
                        "0":"8",
                        "1":null
                    }
                },
                "Set 4":{
                    "I":{
                        "0":"2",
                        "1":10
                    },
                    "II":{
                        "0":"3",
                        "1":13
                    },
                    "III":{
                        "0":"4",
                        "1":15
                    },
                    "IV":{
                        "0":"5",
                        "1":16
                    },
                    "V":{
                        "0":"7",
                        "1":17
                    },
                    "VI":{
                        "0":"9",
                        "1":18
                    }
                },
                "Set 5":0
            },
            "Timeouts 1":{
                "Set 1":{
                    "T":{
                        "0":"5:11"
                    }
                },
                "Set 2":{
                    "T":{

                    }
                },
                "Set 3":{
                    "T":{

                    }
                },
                "Set 4":{
                    "T":{

                    }
                },
                "Set 5":0
            },
            "Timeouts 2":{
                "Set 1":{
                    "T":{

                    }
                },
                "Set 2":{
                    "T":{
                        "0":"13:19"
                    }
                },
                "Set 3":{
                    "T":{
                        "0":"10:13",
                        "1":"11:19"
                    }
                },
                "Set 4":{
                    "T":{
                        "0":"2:5"
                    }
                },
                "Set 5":0
            }
        },
        "Teams":{
            "Name":{
                "Team 1":"QUIMPER VOLLEY 29",
                "Team 2":"RENNES ETUDIANTS CLUB"
            },
            "Players":{
                "Team 1":{
                    "N\u00b0":{
                        "0":1,
                        "1":2,
                        "2":3,
                        "3":5,
                        "4":6,
                        "5":9,
                        "6":10,
                        "7":12,
                        "8":14,
                        "9":15,
                        "10":16
                    },
                    "Nom Pr\u00e9nom":{
                        "0":"BESNEHARD CASSIOPEE",
                        "1":"GAMBOVA BARBORA",
                        "2":"TADIC IVANA",
                        "3":"DENISOVA KARINA",
                        "4":"MORILLON LOLA",
                        "5":"ROBITAILLE KIM",
                        "6":"BOISSELIER LAURA",
                        "7":"DIAGNE MARIEME",
                        "8":"ELOUGA EVA-BROOKLYN",
                        "9":"VOJIKOVA KRISTYNA",
                        "10":"GLAVINIC KATARINA"
                    },
                    "Licence":{
                        "0":1875507,
                        "1":2300069,
                        "2":2298923,
                        "3":2453763,
                        "4":1894383,
                        "5":2409150,
                        "6":1881738,
                        "7":1903745,
                        "8":2046371,
                        "9":2409152,
                        "10":2477734
                    }
                },
                "Team 2":{
                    "N\u00b0":{
                        "0":4,
                        "1":5,
                        "2":7,
                        "3":8,
                        "4":9,
                        "5":11,
                        "6":12,
                        "7":13,
                        "8":14,
                        "9":17
                    },
                    "Nom Pr\u00e9nom":{
                        "0":"PREVERT FLORIANE",
                        "1":"NARBONNE LOUISE",
                        "2":"WARTH NOEMIE",
                        "3":"PICCOLO SOL",
                        "4":"LE MOIGNE LENAIG",
                        "5":"CODIAL OUMAYMA",
                        "6":"HAMON CAMILLE",
                        "7":"OLEMAR KATERINNE-MABEL",
                        "8":"BLANCO ALEOSCAR",
                        "9":"CHOTARD CHRYSTELLE"
                    },
                    "Licence":{
                        "0":1478302,
                        "1":1682168,
                        "2":1995428,
                        "3":2199453,
                        "4":1731845,
                        "5":1991883,
                        "6":1896689,
                        "7":2453649,
                        "8":2453650,
                        "9":1233199
                    }
                }
            },
            "Liberos":{
                "Team 1":{
                    "N\u00b0":{
                        "0":6
                    },
                    "Nom Pr\u00e9nom":{
                        "0":"MORILLON LOLA"
                    },
                    "Licence":{
                        "0":1894383
                    }
                },
                "Team 2":{
                    "N\u00b0":{
                        "0":9
                    },
                    "Nom Pr\u00e9nom":{
                        "0":"LE MOIGNE LENAIG"
                    },
                    "Licence":{
                        "0":1731845
                    }
                }
            },
            "Officials":{
                "Team 1":{
                    "N\u00b0":{
                        "0":"EA",
                        "1":"EB",
                        "2":"SO"
                    },
                    "Nom Pr\u00e9nom":{
                        "0":"HROCH MARTIN",
                        "1":"DUVIVIER DOMINIQUE",
                        "2":"GRIFFON YOANN"
                    },
                    "Licence":{
                        "0":1231908,
                        "1":1228198,
                        "2":2417345
                    }
                },
                "Team 2":{
                    "N\u00b0":{
                        "0":"EA"
                    },
                    "Nom Pr\u00e9nom":{
                        "0":"CHUBILLEAU YANN"
                    },
                    "Licence":{
                        "0":29777
                    }
                }
            }
        },
        "Results":{
            "winner":"QUIMPER VOLLEY 29",
            "score":"3\/1"
        },
        "Referees":{
            "NOM Pr\u00e9nom":{
                "1er":"BAHUAUD NICOLAS",
                "2\u00e8me":"COMBE PHILIPPE",
                "Marqueur":"BRIOIS GAELLE",
                "Marq.Ass":".",
                "R.Salle":"LE PRUNENEC S\u00c9BASTIEN"
            },
            "Ligue":{
                "1er":"PDL",
                "2\u00e8me":"PDL",
                "Marqueur":"BZH",
                "Marq.Ass":null,
                "R.Salle":"BZH"
            },
            "Licence":{
                "1er":1132824.0,
                "2\u00e8me":1468986.0,
                "Marqueur":1555191.0,
                "Marq.Ass":null,
                "R.Salle":2325752.0
            }
        },
        "Penalties":{

        }
    }
}