{
    "Match":{
        "Title":{
            "div_code":"PFA",
            "div_name":"PRE",
            "div_pool":"NATIONALE FEMININES HDF POULE A",
            "match_number":"PFA006",
            "match_day":"02",
            "city":"SAINT ANDRE",
            "gym":"SALLE MARCEL DUCROCQ",
            "category":"SENIOR | FEMININE",
            "ligue":"Ligue HAUTS-DE-FRANCE",
            "date":"2019-10-12 20:00:00",
            "team_1":"SAINT ANDRE 1",
            "team_2":"BERCK SUR MER 1"
        },
        "Sets":{
            "Teams":{
                "Set 1":{
                    "Name":{
                        "Team 1":"BERCK SUR MER 1",
                        "Team 2":"SAINT ANDRE 1"
                    },
                    "Starting":{
                        "Team 1":"Reception",
                        "Team 2":"Service"
                    }
                },
                "Set 2":{
                    "Name":{
                        "Team 1":"BERCK SUR MER 1",
                        "Team 2":"SAINT ANDRE 1"
                    },
                    "Starting":{
                        "Team 1":"Service",
                        "Team 2":"Reception"
                    }
                },
                "Set 3":{
                    "Name":{
                        "Team 1":"BERCK SUR MER 1",
                        "Team 2":"SAINT ANDRE 1"
                    },
                    "Starting":{
                        "Team 1":"Reception",
                        "Team 2":"Service"
                    }
                },
                "Set 4":{
                    "Name":{
                        "Team 1":"BERCK SUR MER 1",
                        "Team 2":"SAINT ANDRE 1"
                    },
                    "Starting":{
                        "Team 1":"Service",
                        "Team 2":"Reception"
                    }
                },
                "Set 5":0
            },
            "Time":{
                "Set 1":{
                    "Time":{
                        "Start":"2019-10-12 19:58:00",
                        "End":"2019-10-12 20:26:00"
                    }
                },
                "Set 2":{
                    "Time":{
                        "Start":"2019-10-12 20:29:00",
                        "End":"2019-10-12 20:56:00"
                    }
                },
                "Set 3":{
                    "Time":{
                        "Start":"2019-10-12 20:59:00",
                        "End":"2019-10-12 21:26:00"
                    }
                },
                "Set 4":{
                    "Time":{
                        "Start":"2019-10-12 21:29:00",
                        "End":"2019-10-12 21:51:00"
                    }
                },
                "Set 5":0
            },
            "Substitutions 1":{
                "Set 1":{
                    "I":{
                        "0":4
                    },
                    "II":{
                        "0":7
                    },
                    "III":{
                        "0":1
                    },
                    "IV":{
                        "0":3
                    },
                    "V":{
                        "0":14
                    },
                    "VI":{
                        "0":10
                    }
                },
                "Set 2":{
                    "I":{
                        "0":4
                    },
                    "II":{
                        "0":7
                    },
                    "III":{
                        "0":1
                    },
                    "IV":{
                        "0":3
                    },
                    "V":{
                        "0":14
                    },
                    "VI":{
                        "0":10
                    }
                },
                "Set 3":{
                    "I":{
                        "0":10
                    },
                    "II":{
                        "0":4
                    },
                    "III":{
                        "0":7
                    },
                    "IV":{
                        "0":1
                    },
                    "V":{
                        "0":3
                    },
                    "VI":{
                        "0":14
                    }
                },
                "Set 4":{
                    "I":{
                        "0":4
                    },
                    "II":{
                        "0":7
                    },
                    "III":{
                        "0":1
                    },
                    "IV":{
                        "0":3
                    },
                    "V":{
                        "0":14
                    },
                    "VI":{
                        "0":10
                    }
                },
                "Set 5":0
            },
            "Substitutions 2":{
                "Set 1":{
                    "I":{
                        "0":"5",
                        "1":"12",
                        "2":"16:23",
                        "3":null
                    },
                    "II":{
                        "0":"10",
                        "1":"9",
                        "2":"13:16",
                        "3":"15:21"
                    },
                    "III":{
                        "0":8.0,
                        "1":null,
                        "2":null,
                        "3":null
                    },
                    "IV":{
                        "0":"3",
                        "1":"14",
                        "2":"16:23",
                        "3":null
                    },
                    "V":{
                        "0":11.0,
                        "1":null,
                        "2":null,
                        "3":null
                    },
                    "VI":{
                        "0":2.0,
                        "1":null,
                        "2":null,
                        "3":null
                    }
                },
                "Set 2":{
                    "I":{
                        "0":2.0,
                        "1":null,
                        "2":null,
                        "3":null
                    },
                    "II":{
                        "0":"5",
                        "1":"3",
                        "2":"17:15",
                        "3":"20:19"
                    },
                    "III":{
                        "0":"10",
                        "1":"1",
                        "2":"14:13",
                        "3":null
                    },
                    "IV":{
                        "0":8.0,
                        "1":null,
                        "2":null,
                        "3":null
                    },
                    "V":{
                        "0":"12",
                        "1":"14",
                        "2":"17:15",
                        "3":"20:19"
                    },
                    "VI":{
                        "0":11.0,
                        "1":null,
                        "2":null,
                        "3":null
                    }
                },
                "Set 3":{
                    "I":{
                        "0":"5",
                        "1":"14",
                        "2":"21:17"
                    },
                    "II":{
                        "0":"10",
                        "1":"1",
                        "2":"19:15"
                    },
                    "III":{
                        "0":"8",
                        "1":"4",
                        "2":"17:13"
                    },
                    "IV":{
                        "0":12.0,
                        "1":null,
                        "2":null
                    },
                    "V":{
                        "0":11.0,
                        "1":null,
                        "2":null
                    },
                    "VI":{
                        "0":2.0,
                        "1":null,
                        "2":null
                    }
                },
                "Set 4":{
                    "I":{
                        "0":2.0,
                        "1":null,
                        "2":null
                    },
                    "II":{
                        "0":"5",
                        "1":"14",
                        "2":"12:7"
                    },
                    "III":{
                        "0":"10",
                        "1":"1",
                        "2":"19:7"
                    },
                    "IV":{
                        "0":4.0,
                        "1":null,
                        "2":null
                    },
                    "V":{
                        "0":"12",
                        "1":"3",
                        "2":"21:7"
                    },
                    "VI":{
                        "0":"11",
                        "1":"9",
                        "2":"18:7"
                    }
                },
                "Set 5":0
            },
            "Serves 1":{
                "Set 1":{
                    "I":{
                        "0":null,
                        "1":14.0,
                        "2":25.0
                    },
                    "II":{
                        "0":"5",
                        "1":16.0,
                        "2":null
                    },
                    "III":{
                        "0":"7",
                        "1":18.0,
                        "2":null
                    },
                    "IV":{
                        "0":"8",
                        "1":19.0,
                        "2":null
                    },
                    "V":{
                        "0":"10",
                        "1":23.0,
                        "2":null
                    },
                    "VI":{
                        "0":"13",
                        "1":24.0,
                        "2":null
                    }
                },
                "Set 2":{
                    "I":{
                        "0":"0",
                        "1":11,
                        "2":19
                    },
                    "II":{
                        "0":"1",
                        "1":13,
                        "2":20
                    },
                    "III":{
                        "0":"2",
                        "1":14,
                        "2":21
                    },
                    "IV":{
                        "0":"3",
                        "1":15.0,
                        "2":null
                    },
                    "V":{
                        "0":"4",
                        "1":17.0,
                        "2":null
                    },
                    "VI":{
                        "0":"5",
                        "1":18.0,
                        "2":null
                    }
                },
                "Set 3":{
                    "I":{
                        "0":null,
                        "1":14.0
                    },
                    "II":{
                        "0":"2",
                        "1":15
                    },
                    "III":{
                        "0":"4",
                        "1":17
                    },
                    "IV":{
                        "0":"5",
                        "1":18
                    },
                    "V":{
                        "0":"12",
                        "1":19
                    },
                    "VI":{
                        "0":"13",
                        "1":null
                    }
                },
                "Set 4":{
                    "I":{
                        "0":"1",
                        "1":11
                    },
                    "II":{
                        "0":"3",
                        "1":12
                    },
                    "III":{
                        "0":"4",
                        "1":null
                    },
                    "IV":{
                        "0":"6",
                        "1":null
                    },
                    "V":{
                        "0":"7",
                        "1":null
                    },
                    "VI":{
                        "0":"9",
                        "1":null
                    }
                },
                "Set 5":0
            },
            "Serves 2":{
                "Set 1":{
                    "I":{
                        "0":"1",
                        "1":12
                    },
                    "II":{
                        "0":"2",
                        "1":13
                    },
                    "III":{
                        "0":"4",
                        "1":14
                    },
                    "IV":{
                        "0":"7",
                        "1":15
                    },
                    "V":{
                        "0":"9",
                        "1":16
                    },
                    "VI":{
                        "0":"10",
                        "1":18
                    }
                },
                "Set 2":{
                    "I":{
                        "0":null,
                        "1":10.0,
                        "2":19.0
                    },
                    "II":{
                        "0":"2",
                        "1":13,
                        "2":21
                    },
                    "III":{
                        "0":"3",
                        "1":14,
                        "2":22
                    },
                    "IV":{
                        "0":"4",
                        "1":16,
                        "2":25
                    },
                    "V":{
                        "0":"5",
                        "1":17.0,
                        "2":null
                    },
                    "VI":{
                        "0":"6",
                        "1":18.0,
                        "2":null
                    }
                },
                "Set 3":{
                    "I":{
                        "0":"2",
                        "1":18
                    },
                    "II":{
                        "0":"3",
                        "1":20
                    },
                    "III":{
                        "0":"6",
                        "1":22
                    },
                    "IV":{
                        "0":"10",
                        "1":24
                    },
                    "V":{
                        "0":"14",
                        "1":25
                    },
                    "VI":{
                        "0":"17",
                        "1":null
                    }
                },
                "Set 4":{
                    "I":{
                        "0":null,
                        "1":22.0
                    },
                    "II":{
                        "0":"6",
                        "1":23
                    },
                    "III":{
                        "0":"7",
                        "1":25
                    },
                    "IV":{
                        "0":"8",
                        "1":null
                    },
                    "V":{
                        "0":"10",
                        "1":null
                    },
                    "VI":{
                        "0":"21",
                        "1":null
                    }
                },
                "Set 5":0
            },
            "Timeouts 1":{
                "Set 1":{
                    "T":{

                    }
                },
                "Set 2":{
                    "T":{
                        "0":"19:21",
                        "1":"21:24"
                    }
                },
                "Set 3":{
                    "T":{
                        "0":"15:20",
                        "1":"17:22"
                    }
                },
                "Set 4":{
                    "T":{
                        "0":"7:12",
                        "1":"7:20"
                    }
                },
                "Set 5":0
            },
            "Timeouts 2":{
                "Set 1":{
                    "T":{
                        "0":"1:5",
                        "1":"15:22"
                    }
                },
                "Set 2":{
                    "T":{

                    }
                },
                "Set 3":{
                    "T":{
                        "0":"10:12"
                    }
                },
                "Set 4":{
                    "T":{

                    }
                },
                "Set 5":0
            }
        },
        "Teams":{
            "Name":{
                "Team 1":"BERCK SUR MER 1",
                "Team 2":"SAINT ANDRE 1"
            },
            "Players":{
                "Team 1":{
                    "N\u00b0":{
                        "0":1,
                        "1":3,
                        "2":4,
                        "3":7,
                        "4":10,
                        "5":14,
                        "6":16
                    },
                    "Nom Pr\u00e9nom":{
                        "0":"CARNIN MARIE",
                        "1":"JOLY ALIX",
                        "2":"OUIN MATHILDE",
                        "3":"DELPIERRE CAROLINE",
                        "4":"VANHERSECKE JULIETTE",
                        "5":"LAMOUR CAMILLE",
                        "6":"FOCKERMANN AM\u00e9LIE"
                    },
                    "Licence":{
                        "0":1765495,
                        "1":2190059,
                        "2":1601486,
                        "3":1515843,
                        "4":1901655,
                        "5":1453441,
                        "6":2088701
                    }
                },
                "Team 2":{
                    "N\u00b0":{
                        "0":1,
                        "1":2,
                        "2":3,
                        "3":4,
                        "4":5,
                        "5":8,
                        "6":9,
                        "7":10,
                        "8":11,
                        "9":12,
                        "10":14,
                        "11":15
                    },
                    "Nom Pr\u00e9nom":{
                        "0":"MALET MATHILDE",
                        "1":"HOCHEDEZ ALIX",
                        "2":"BOLLON HELENE",
                        "3":"LEONE ALEXANDRA",
                        "4":"LIENARD MARGOT",
                        "5":"LEVANT FANNY",
                        "6":"DRICI ORNELA",
                        "7":"CARETTE DORINE",
                        "8":"DRICI ANXHELA",
                        "9":"WANNEBROUCQ MARIE",
                        "10":"DELEVAL LAURA",
                        "11":"LEMAIRE CORALIE"
                    },
                    "Licence":{
                        "0":1468432,
                        "1":1814549,
                        "2":1825741,
                        "3":1650411,
                        "4":1759012,
                        "5":1944837,
                        "6":1997351,
                        "7":1769851,
                        "8":2011806,
                        "9":1904845,
                        "10":1530436,
                        "11":1924445
                    }
                }
            },
            "Liberos":{
                "Team 1":{
                    "N\u00b0":{
                        "0":16
                    },
                    "Nom Pr\u00e9nom":{
                        "0":"FOCKERMANN AM\u00e9LIE"
                    },
                    "Licence":{
                        "0":2088701
                    }
                },
                "Team 2":{
                    "N\u00b0":{
                        "0":15
                    },
                    "Nom Pr\u00e9nom":{
                        "0":"LEMAIRE CORALIE"
                    },
                    "Licence":{
                        "0":1924445
                    }
                }
            },
            "Officials":{
                "Team 1":{
                    "N\u00b0":{
                        "0":"EA"
                    },
                    "Nom Pr\u00e9nom":{
                        "0":"VANBELLE ARTHUR"
                    },
                    "Licence":{
                        "0":1803426
                    }
                },
                "Team 2":{
                    "N\u00b0":{
                        "0":"EA"
                    },
                    "Nom Pr\u00e9nom":{
                        "0":"OUENOUGHI BOUBEKEUR"
                    },
                    "Licence":{
                        "0":2305605
                    }
                }
            }
        },
        "Results":{
            "winner":"SAINT ANDRE 1",
            "score":"3\/1"
        },
        "Referees":{
            "NOM Pr\u00e9nom":{
                "1er":"RICHART OLIVIER",
                "2\u00e8me":null,
                "Marqueur":"DEFRANCE HERVE",
                "Marq.Ass":".",
                "nan":null
            },
            "Ligue":{
                "1er":"HDF",
                "2\u00e8me":null,
                "Marqueur":"HDF",
                "Marq.Ass":null,
                "nan":"Juges"
            },
            "Licence":{
                "1er":2218549.0,
                "2\u00e8me":null,
                "Marqueur":1943419.0,
                "Marq.Ass":null,
                "nan":null
            }
        },
        "Penalties":{

        }
    }
}