{
    "Match":{
        "Title":{
            "div_code":"2FD ",
            "div_name":"NATIONALE 2 FEMININE",
            "div_pool":"POULE D",
            "match_number":"2FD008",
            "match_day":"02",
            "city":"VANDOEUVRE-LES-NANCY",
            "gym":"MONPLAISIR",
            "category":"SENIOR | FEMININE",
            "ligue":"Comp\u00e9titions Nationales SENIORS",
            "date":"2019-10-13 14:00:00"
        },
        "Sets":{
            "Teams":{
                "Set 1":{
                    "Name":{
                        "Team A":"VANDOEUVRE-NANCY VOLLE",
                        "Team B":"CLUB OMNISPORTS DE SAI"
                    },
                    "Starting":{
                        "Team A":"Service",
                        "Team B":"Reception"
                    }
                },
                "Set 2":{
                    "Name":{
                        "Team A":"VANDOEUVRE-NANCY VOLLE",
                        "Team B":"CLUB OMNISPORTS DE SAI"
                    },
                    "Starting":{
                        "Team A":"Reception",
                        "Team B":"Service"
                    }
                },
                "Set 3":{
                    "Name":{
                        "Team A":"VANDOEUVRE-NANCY VOLLE",
                        "Team B":"CLUB OMNISPORTS DE SAI"
                    },
                    "Starting":{
                        "Team A":"Service",
                        "Team B":"Reception"
                    }
                },
                "Set 4":{
                    "Name":{
                        "Team A":"VANDOEUVRE-NANCY VOLLE",
                        "Team B":"CLUB OMNISPORTS DE SAI"
                    },
                    "Starting":{
                        "Team A":"Reception",
                        "Team B":"Service"
                    }
                },
                "Set 5":0
            },
            "Time":{
                "Set 1":{
                    "Time":{
                        "Start":"2019-10-13 13:58:00",
                        "End":"2019-10-13 14:25:00"
                    }
                },
                "Set 2":{
                    "Time":{
                        "Start":"2019-10-13 14:28:00",
                        "End":"2019-10-13 14:53:00"
                    }
                },
                "Set 3":{
                    "Time":{
                        "Start":"2019-10-13 14:56:00",
                        "End":"2019-10-13 15:24:00"
                    }
                },
                "Set 4":{
                    "Time":{
                        "Start":"2019-10-13 15:28:00",
                        "End":"2019-10-13 15:54:00"
                    }
                },
                "Set 5":0
            },
            "Substitutions A":{
                "Set 1":{
                    "I":{
                        "0":16
                    },
                    "II":{
                        "0":12
                    },
                    "III":{
                        "0":5
                    },
                    "IV":{
                        "0":4
                    },
                    "V":{
                        "0":7
                    },
                    "VI":{
                        "0":20
                    }
                },
                "Set 2":{
                    "I":{
                        "0":"12",
                        "1":"14",
                        "2":"14:19"
                    },
                    "II":{
                        "0":"11",
                        "1":"3",
                        "2":"15:21"
                    },
                    "III":{
                        "0":4.0,
                        "1":null,
                        "2":null
                    },
                    "IV":{
                        "0":7.0,
                        "1":null,
                        "2":null
                    },
                    "V":{
                        "0":20.0,
                        "1":null,
                        "2":null
                    },
                    "VI":{
                        "0":16.0,
                        "1":null,
                        "2":null
                    }
                },
                "Set 3":{
                    "I":{
                        "0":16.0,
                        "1":null,
                        "2":null
                    },
                    "II":{
                        "0":"12",
                        "1":"14",
                        "2":"20:18"
                    },
                    "III":{
                        "0":5.0,
                        "1":null,
                        "2":null
                    },
                    "IV":{
                        "0":4.0,
                        "1":null,
                        "2":null
                    },
                    "V":{
                        "0":"20",
                        "1":"11",
                        "2":"20:19"
                    },
                    "VI":{
                        "0":7.0,
                        "1":null,
                        "2":null
                    }
                },
                "Set 4":{
                    "I":{
                        "0":"14",
                        "1":"12",
                        "2":"11:17",
                        "3":null
                    },
                    "II":{
                        "0":20.0,
                        "1":null,
                        "2":null,
                        "3":null
                    },
                    "III":{
                        "0":4.0,
                        "1":null,
                        "2":null,
                        "3":null
                    },
                    "IV":{
                        "0":11.0,
                        "1":null,
                        "2":null,
                        "3":null
                    },
                    "V":{
                        "0":"7",
                        "1":"3",
                        "2":"13:18",
                        "3":"20:20"
                    },
                    "VI":{
                        "0":16.0,
                        "1":null,
                        "2":null,
                        "3":null
                    }
                },
                "Set 5":0
            },
            "Substitutions B":{
                "Set 1":{
                    "I":{
                        "0":2.0,
                        "1":null,
                        "2":null
                    },
                    "II":{
                        "0":13.0,
                        "1":null,
                        "2":null
                    },
                    "III":{
                        "0":4.0,
                        "1":null,
                        "2":null
                    },
                    "IV":{
                        "0":11.0,
                        "1":null,
                        "2":null
                    },
                    "V":{
                        "0":9.0,
                        "1":null,
                        "2":null
                    },
                    "VI":{
                        "0":"8",
                        "1":"12",
                        "2":"17:20"
                    }
                },
                "Set 2":{
                    "I":{
                        "0":13.0,
                        "1":null,
                        "2":null
                    },
                    "II":{
                        "0":4.0,
                        "1":null,
                        "2":null
                    },
                    "III":{
                        "0":11.0,
                        "1":null,
                        "2":null
                    },
                    "IV":{
                        "0":"9",
                        "1":"3",
                        "2":"23:19"
                    },
                    "V":{
                        "0":12.0,
                        "1":null,
                        "2":null
                    },
                    "VI":{
                        "0":2.0,
                        "1":null,
                        "2":null
                    }
                },
                "Set 3":{
                    "I":{
                        "0":2.0,
                        "1":null,
                        "2":null
                    },
                    "II":{
                        "0":13.0,
                        "1":null,
                        "2":null
                    },
                    "III":{
                        "0":4.0,
                        "1":null,
                        "2":null
                    },
                    "IV":{
                        "0":11.0,
                        "1":null,
                        "2":null
                    },
                    "V":{
                        "0":"9",
                        "1":"3",
                        "2":"10:12"
                    },
                    "VI":{
                        "0":"12",
                        "1":"8",
                        "2":"13:17"
                    }
                },
                "Set 4":{
                    "I":{
                        "0":13.0,
                        "1":null,
                        "2":null,
                        "3":null
                    },
                    "II":{
                        "0":4.0,
                        "1":null,
                        "2":null,
                        "3":null
                    },
                    "III":{
                        "0":"2",
                        "1":"3",
                        "2":"10:9",
                        "3":"19:17"
                    },
                    "IV":{
                        "0":"9",
                        "1":"12",
                        "2":"18:16",
                        "3":null
                    },
                    "V":{
                        "0":8.0,
                        "1":null,
                        "2":null,
                        "3":null
                    },
                    "VI":{
                        "0":11.0,
                        "1":null,
                        "2":null,
                        "3":null
                    }
                },
                "Set 5":0
            },
            "Serves A":{
                "Set 1":{
                    "I":{
                        "0":"3",
                        "1":14,
                        "2":25
                    },
                    "II":{
                        "0":"5",
                        "1":16.0,
                        "2":null
                    },
                    "III":{
                        "0":"8",
                        "1":17.0,
                        "2":null
                    },
                    "IV":{
                        "0":"9",
                        "1":18.0,
                        "2":null
                    },
                    "V":{
                        "0":"12",
                        "1":23.0,
                        "2":null
                    },
                    "VI":{
                        "0":"13",
                        "1":24.0,
                        "2":null
                    }
                },
                "Set 2":{
                    "I":{
                        "0":null,
                        "1":9.0,
                        "2":16.0
                    },
                    "II":{
                        "0":"2",
                        "1":10,
                        "2":19
                    },
                    "III":{
                        "0":"4",
                        "1":12,
                        "2":20
                    },
                    "IV":{
                        "0":"6",
                        "1":13.0,
                        "2":null
                    },
                    "V":{
                        "0":"7",
                        "1":14.0,
                        "2":null
                    },
                    "VI":{
                        "0":"8",
                        "1":15.0,
                        "2":null
                    }
                },
                "Set 3":{
                    "I":{
                        "0":"0",
                        "1":9,
                        "2":20
                    },
                    "II":{
                        "0":"1",
                        "1":11,
                        "2":21
                    },
                    "III":{
                        "0":"2",
                        "1":13,
                        "2":25
                    },
                    "IV":{
                        "0":"5",
                        "1":14.0,
                        "2":null
                    },
                    "V":{
                        "0":"7",
                        "1":17.0,
                        "2":null
                    },
                    "VI":{
                        "0":"8",
                        "1":19.0,
                        "2":null
                    }
                },
                "Set 4":{
                    "I":{
                        "0":null,
                        "1":8.0,
                        "2":16.0
                    },
                    "II":{
                        "0":"1",
                        "1":9,
                        "2":17
                    },
                    "III":{
                        "0":"2",
                        "1":9,
                        "2":20
                    },
                    "IV":{
                        "0":"4",
                        "1":10.0,
                        "2":null
                    },
                    "V":{
                        "0":"5",
                        "1":11.0,
                        "2":null
                    },
                    "VI":{
                        "0":"6",
                        "1":13.0,
                        "2":null
                    }
                },
                "Set 5":0
            },
            "Serves B":{
                "Set 1":{
                    "I":{
                        "0":null,
                        "1":12.0,
                        "2":21.0
                    },
                    "II":{
                        "0":"1",
                        "1":13.0,
                        "2":null
                    },
                    "III":{
                        "0":"5",
                        "1":14.0,
                        "2":null
                    },
                    "IV":{
                        "0":"6",
                        "1":16.0,
                        "2":null
                    },
                    "V":{
                        "0":"9",
                        "1":17.0,
                        "2":null
                    },
                    "VI":{
                        "0":"10",
                        "1":19.0,
                        "2":null
                    }
                },
                "Set 2":{
                    "I":{
                        "0":"0",
                        "1":13,
                        "2":22
                    },
                    "II":{
                        "0":"1",
                        "1":15,
                        "2":24
                    },
                    "III":{
                        "0":"5",
                        "1":16,
                        "2":25
                    },
                    "IV":{
                        "0":"7",
                        "1":17.0,
                        "2":null
                    },
                    "V":{
                        "0":"9",
                        "1":19.0,
                        "2":null
                    },
                    "VI":{
                        "0":"12",
                        "1":21.0,
                        "2":null
                    }
                },
                "Set 3":{
                    "I":{
                        "0":null,
                        "1":8.0,
                        "2":16.0
                    },
                    "II":{
                        "0":"1",
                        "1":9,
                        "2":20
                    },
                    "III":{
                        "0":"4",
                        "1":10,
                        "2":21
                    },
                    "IV":{
                        "0":"5",
                        "1":12.0,
                        "2":null
                    },
                    "V":{
                        "0":"6",
                        "1":13.0,
                        "2":null
                    },
                    "VI":{
                        "0":"7",
                        "1":15.0,
                        "2":null
                    }
                },
                "Set 4":{
                    "I":{
                        "0":"0",
                        "1":10,
                        "2":19
                    },
                    "II":{
                        "0":"2",
                        "1":12,
                        "2":20
                    },
                    "III":{
                        "0":"3",
                        "1":13,
                        "2":25
                    },
                    "IV":{
                        "0":"6",
                        "1":16.0,
                        "2":null
                    },
                    "V":{
                        "0":"7",
                        "1":17.0,
                        "2":null
                    },
                    "VI":{
                        "0":"8",
                        "1":18.0,
                        "2":null
                    }
                },
                "Set 5":0
            },
            "Timeouts A":{
                "Set 1":{
                    "T":{

                    }
                },
                "Set 2":{
                    "T":{
                        "0":"8:12",
                        "1":"13:17"
                    }
                },
                "Set 3":{
                    "T":{
                        "0":"20:20"
                    }
                },
                "Set 4":{
                    "Unnamed: 0":{
                        "0":null,
                        "1":"20:23"
                    },
                    "T":{
                        "0":"10:15",
                        "1":null
                    }
                },
                "Set 5":0
            },
            "Timeouts B":{
                "Set 1":{
                    "T":{
                        "0":"17:23",
                        "1":"19:24"
                    }
                },
                "Set 2":{
                    "T":{
                        "0":"22:18"
                    }
                },
                "Set 3":{
                    "T":{
                        "0":"20:21",
                        "1":"21:23"
                    }
                },
                "Set 4":{
                    "T":{
                        "0":"18:15"
                    }
                },
                "Set 5":0
            }
        },
        "Teams":{
            "Name":{
                "Team 1":[
                    "VANDOEUVRE-NANCY VOLLEY-BALL"
                ],
                "Team 2":[
                    "CLUB OMNISPORTS DE SAINT-FONS"
                ]
            },
            "Players":{
                "Team 1":{
                    "N\u00b0":{
                        "0":2,
                        "1":3,
                        "2":4,
                        "3":5,
                        "4":6,
                        "5":7,
                        "6":11,
                        "7":12,
                        "8":14,
                        "9":15,
                        "10":16,
                        "11":20
                    },
                    "Nom Pr\u00e9nom":{
                        "0":"TRITZ APOLLINE",
                        "1":"CABROL MANON",
                        "2":"FLORENTINY LAURA",
                        "3":"VILLEM CAROLINE",
                        "4":"SIMON MARINE",
                        "5":"DJILALI ALEXIA",
                        "6":"BARBIER CAMILLE",
                        "7":"HENRY MANON",
                        "8":"BAUDU HELENA",
                        "9":"BETZ ZOE",
                        "10":"ZENGA ABALA GRACE CHRISTINE",
                        "11":"DULEVA NIKOL"
                    },
                    "Licence":{
                        "0":1893191,
                        "1":2197773,
                        "2":2167227,
                        "3":1973047,
                        "4":1866888,
                        "5":1547734,
                        "6":2085566,
                        "7":1910114,
                        "8":1945041,
                        "9":1849233,
                        "10":1994977,
                        "11":2412543
                    }
                },
                "Team 2":{
                    "N\u00b0":{
                        "0":2,
                        "1":3,
                        "2":4,
                        "3":7,
                        "4":8,
                        "5":9,
                        "6":11,
                        "7":12,
                        "8":13
                    },
                    "Nom Pr\u00e9nom":{
                        "0":"IRABE ARMELLE",
                        "1":"ALLIOD MARGOT",
                        "2":"MAKHLOUF ANISSA",
                        "3":"RANC MATHILDE",
                        "4":"SIMOES JOANA",
                        "5":"AZIABOU IMELDA",
                        "6":"DANTHON CYNTHIA",
                        "7":"MUNSCH THAIS",
                        "8":"MCKIBBEN KIARA"
                    },
                    "Licence":{
                        "0":1412952,
                        "1":1799397,
                        "2":1455068,
                        "3":1944952,
                        "4":1834805,
                        "5":1861140,
                        "6":1407080,
                        "7":2154186,
                        "8":2410572
                    }
                }
            },
            "Liberos":{
                "Team 1":{
                    "N\u00b0":{
                        "0":2,
                        "1":15
                    },
                    "Nom Pr\u00e9nom":{
                        "0":"TRITZ APOLLINE",
                        "1":"BETZ ZOE"
                    },
                    "Licence":{
                        "0":1893191,
                        "1":1849233
                    }
                },
                "Team 2":{
                    "N\u00b0":{
                        "0":7
                    },
                    "Nom Pr\u00e9nom":{
                        "0":"RANC MATHILDE"
                    },
                    "Licence":{
                        "0":1944952
                    }
                }
            },
            "Officials":{
                "Team 1":{
                    "N\u00b0":{
                        "0":"EA",
                        "1":"EB",
                        "2":"SO"
                    },
                    "Nom Pr\u00e9nom":{
                        "0":"HANEGREEFS J\u00c9R\u00d4ME",
                        "1":"BETZ RAPHA\u00cbL",
                        "2":"ALT GUY"
                    },
                    "Licence":{
                        "0":1916301,
                        "1":2141719,
                        "2":1804917
                    }
                },
                "Team 2":{
                    "N\u00b0":{
                        "0":"EA"
                    },
                    "Nom Pr\u00e9nom":{
                        "0":"BOCCALI MARC-ANTOINE"
                    },
                    "Licence":{
                        "0":2405641
                    }
                }
            }
        },
        "Results":{
            "winner":0,
            "score":"0\/0"
        },
        "Referees":{
            "NOM Pr\u00e9nom":{
                "1er":"JOUCHT ABDELLAH",
                "2\u00e8me":"LEPAGE BENOIT",
                "Marqueur":null,
                "Marq.Ass":".",
                "nan":null
            },
            "Ligue":{
                "1er":"LIG_GES",
                "2\u00e8me":"LIG_GES",
                "Marqueur":null,
                "Marq.Ass":null,
                "nan":"Juges"
            },
            "Licence":{
                "1er":1959328.0,
                "2\u00e8me":1209434.0,
                "Marqueur":null,
                "Marq.Ass":null,
                "nan":null
            }
        },
        "Penalties":{

        }
    }
}